GithubMiji/README.md
GithubMiji/__init__.py
GithubMiji/__main__.py
GithubMiji/file.epub
GithubMiji/index.html
GithubMiji/css/__init__.py
GithubMiji/css/annotations.css
GithubMiji/css/main.css
GithubMiji/css/normalize.css
GithubMiji/css/popup.css
GithubMiji/font/__init__.py
GithubMiji/font/fontello.eot
GithubMiji/font/fontello.svg
GithubMiji/font/fontello.ttf
GithubMiji/font/fontello.woff
GithubMiji/img/__init__.py
GithubMiji/img/annotator-glyph-sprite.png
GithubMiji/img/annotator-icon-sprite.png
GithubMiji/img/apple-touch-icon.png
GithubMiji/img/cancelfullscreen.png
GithubMiji/img/close.png
GithubMiji/img/fullscreen.png
GithubMiji/img/loader.gif
GithubMiji/img/menu-icon.png
GithubMiji/img/save.png
GithubMiji/img/saved.png
GithubMiji/img/settings-s.png
GithubMiji/img/settings.png
GithubMiji/img/star.png
GithubMiji/js/__init__.py
GithubMiji/js/epub.js
GithubMiji/js/epub.min.js
GithubMiji/js/epub.min.map
GithubMiji/js/hooks.min.js
GithubMiji/js/hooks.min.map
GithubMiji/js/reader.js
GithubMiji/js/reader.js.map
GithubMiji/js/reader.min.js
GithubMiji/js/reader.min.map
GithubMiji/js/hooks/__init__.py
GithubMiji/js/hooks/extensions/__init__.py
GithubMiji/js/hooks/extensions/highlight.js
GithubMiji/js/libs/__init__.py
GithubMiji/js/libs/jquery.min.js
GithubMiji/js/libs/localforage.min.js
GithubMiji/js/libs/screenfull.js
GithubMiji/js/libs/screenfull.min.js
GithubMiji/js/libs/zip.min.js
GithubMiji/js/plugins/__init__.py
GithubMiji/js/plugins/hypothesis.js
GithubMiji/js/plugins/search.js
github_miji-2024.3.1.0.dist-info/METADATA
github_miji-2024.3.1.0.dist-info/WHEEL
github_miji-2024.3.1.0.dist-info/entry_points.txt
github_miji-2024.3.1.0.dist-info/top_level.txt
github_miji-2024.3.1.0.dist-info/RECORD
